README.md
setup.py
littlejo_cilium/__init__.py
littlejo_cilium/_inputs.py
littlejo_cilium/_utilities.py
littlejo_cilium/clustermesh.py
littlejo_cilium/clustermesh_connection.py
littlejo_cilium/config.py
littlejo_cilium/deploy.py
littlejo_cilium/get_helm_values.py
littlejo_cilium/hubble.py
littlejo_cilium/install.py
littlejo_cilium/kubeproxy_free.py
littlejo_cilium/outputs.py
littlejo_cilium/provider.py
littlejo_cilium/pulumi-plugin.json
littlejo_cilium/py.typed
littlejo_cilium.egg-info/PKG-INFO
littlejo_cilium.egg-info/SOURCES.txt
littlejo_cilium.egg-info/dependency_links.txt
littlejo_cilium.egg-info/not-zip-safe
littlejo_cilium.egg-info/requires.txt
littlejo_cilium.egg-info/top_level.txt
littlejo_cilium/config/__init__.py
littlejo_cilium/config/vars.py