Metadata-Version: 2.1
Name: littlejo-cilium
Version: 0.2.1
Summary: A Pulumi package for creating and managing Cilium resources
Home-page: https://github.com/littlejo/pulumi-cilium
License: Apache-2.0
Project-URL: Repository, https://github.com/littlejo/pulumi-cilium
Keywords: pulumi cilium category/network
Requires-Python: >=3.9
